folder_structure_creator/__init__.py
folder_structure_creator/fstruct.py
tests/__init__.py
tests/test_fstruct.py
folder_structure_creator-0.4.0.dist-info/LICENSE
folder_structure_creator-0.4.0.dist-info/METADATA
folder_structure_creator-0.4.0.dist-info/WHEEL
folder_structure_creator-0.4.0.dist-info/entry_points.txt
folder_structure_creator-0.4.0.dist-info/top_level.txt
folder_structure_creator-0.4.0.dist-info/RECORD
