Metadata-Version: 2.1
Name: folder-structure-creator
Version: 0.4.0
Summary: A tool to create folder structures based on text files
Home-page: https://github.com/NagiEight/folder-structure-creator
Author: NagiEight
Author-email: nagieight22@gmail.com
Classifier: Programming Language :: Python :: 3
Classifier: License :: OSI Approved :: MIT License
Classifier: Operating System :: OS Independent
License-File: LICENSE
